odoo/addons/web_no_bubble/README.rst
odoo/addons/web_no_bubble/__init__.py
odoo/addons/web_no_bubble/__manifest__.py
odoo/addons/web_no_bubble/i18n/ca.po
odoo/addons/web_no_bubble/i18n/es.po
odoo/addons/web_no_bubble/i18n/fr_FR.po
odoo/addons/web_no_bubble/i18n/hr.po
odoo/addons/web_no_bubble/i18n/pt_BR.po
odoo/addons/web_no_bubble/i18n/web_no_bubble.pot
odoo/addons/web_no_bubble/i18n/zh_CN.po
odoo/addons/web_no_bubble/readme/CONTRIBUTORS.rst
odoo/addons/web_no_bubble/readme/DESCRIPTION.rst
odoo/addons/web_no_bubble/static/description/icon.png
odoo/addons/web_no_bubble/static/description/index.html
odoo/addons/web_no_bubble/static/src/css/web_no_bubble.scss
odoo/addons/web_no_bubble/views/web_no_bubble.xml
odoo12_addon_web_no_bubble-12.0.1.0.0.99.dev12.dist-info/METADATA
odoo12_addon_web_no_bubble-12.0.1.0.0.99.dev12.dist-info/WHEEL
odoo12_addon_web_no_bubble-12.0.1.0.0.99.dev12.dist-info/top_level.txt
odoo12_addon_web_no_bubble-12.0.1.0.0.99.dev12.dist-info/RECORD
